boiler/__init__.py
boiler/definitions.py
boiler/models.py
boiler/validate.py
boiler/aws/fileupload.py
boiler/commands/__init__.py
boiler/commands/activity.py
boiler/commands/kpf.py
boiler/commands/kw18.py
boiler/commands/utils.py
boiler/commands/vendor.py
boiler/commands/video.py
boiler/serialization/__init__.py
boiler/serialization/kpf.py
boiler/serialization/kw18.py
boiler/serialization/web.py
diva_boiler-0.0.7.dist-info/METADATA
diva_boiler-0.0.7.dist-info/WHEEL
diva_boiler-0.0.7.dist-info/entry_points.txt
diva_boiler-0.0.7.dist-info/top_level.txt
diva_boiler-0.0.7.dist-info/RECORD
