Metadata-Version: 2.1
Name: diva-boiler
Version: 0.0.7
Summary: a cli for interacting with stumpf server
Home-page: UNKNOWN
Author: Kitware, Inc.
Author-email: kitware@kitware.com
License: Apache Software License 2.0
Platform: UNKNOWN
Requires-Dist: attrs
Requires-Dist: boto3
Requires-Dist: click (>=7.0)
Requires-Dist: pyyaml
Requires-Dist: requests
Requires-Dist: requests-toolbelt
